alliance_platform/ui/__init__.py
alliance_platform/ui/apps.py
alliance_platform/ui/forms/__init__.py
alliance_platform/ui/forms/renderers.py
alliance_platform/ui/py.typed
alliance_platform/ui/settings.py
alliance_platform/ui/templates/alliance_platform/ui/labeled_input_base.html
alliance_platform/ui/templatetags/alliance_platform/__init__.py
alliance_platform/ui/templatetags/alliance_platform/button.py
alliance_platform/ui/templatetags/alliance_platform/date_picker.py
alliance_platform/ui/templatetags/alliance_platform/form.py
alliance_platform/ui/templatetags/alliance_platform/icon.py
alliance_platform/ui/templatetags/alliance_platform/inline_alert.py
alliance_platform/ui/templatetags/alliance_platform/labeled_input.py
alliance_platform/ui/templatetags/alliance_platform/menubar.py
alliance_platform/ui/templatetags/alliance_platform/misc.py
alliance_platform/ui/templatetags/alliance_platform/pagination.py
alliance_platform/ui/templatetags/alliance_platform/table.py
alliance_platform/ui/templatetags/alliance_platform/time_input.py
alliance_platform/ui/templatetags/alliance_platform/ui.py
alliance_platform/ui/templatetags/alliance_platform/utils.py
alliance_platform_ui-0.0.1.dist-info/METADATA
alliance_platform_ui-0.0.1.dist-info/WHEEL
alliance_platform_ui-0.0.1.dist-info/entry_points.txt
alliance_platform_ui-0.0.1.dist-info/RECORD
